streamlitextras/__init__.py
streamlitextras/helpers.py
streamlitextras/storageservice.py
streamlitextras/utils.py
streamlitextras/webutils.py
streamlitextras/authenticator/__init__.py
streamlitextras/authenticator/exceptions.py
streamlitextras/authenticator/user.py
streamlitextras/authenticator/utils.py
streamlitextras/cookiemanager/__init__.py
streamlitextras/cookiemanager/frontend/build/asset-manifest.json
streamlitextras/cookiemanager/frontend/build/index.html
streamlitextras/cookiemanager/frontend/build/precache-manifest.d091de9fa4668477ba52acdbecc2c864.js
streamlitextras/cookiemanager/frontend/build/service-worker.js
streamlitextras/cookiemanager/frontend/build/static/js/2.2bc12ddb.chunk.js
streamlitextras/cookiemanager/frontend/build/static/js/2.2bc12ddb.chunk.js.LICENSE.txt
streamlitextras/cookiemanager/frontend/build/static/js/2.2bc12ddb.chunk.js.map
streamlitextras/cookiemanager/frontend/build/static/js/main.a8b332f3.chunk.js
streamlitextras/cookiemanager/frontend/build/static/js/main.a8b332f3.chunk.js.map
streamlitextras/cookiemanager/frontend/build/static/js/runtime-main.41b280b5.js
streamlitextras/cookiemanager/frontend/build/static/js/runtime-main.41b280b5.js.map
streamlitextras/logger/__init__.py
streamlitextras/logger/firebasesink.py
streamlitextras/router/__init__.py
streamlitextras/threader/__init__.py
streamlit_base_extras-0.2.45.dist-info/LICENCE
streamlit_base_extras-0.2.45.dist-info/METADATA
streamlit_base_extras-0.2.45.dist-info/WHEEL
streamlit_base_extras-0.2.45.dist-info/top_level.txt
streamlit_base_extras-0.2.45.dist-info/RECORD
