Metadata-Version: 2.1
Name: streamlit-base-extras
Version: 0.2.45
Summary: Make building with streamlit easier.
Home-page: https://github.com/blipk/streamlitextras
Download-URL: https://github.com/blipk/streamlitextras/archive/0.2.45.tar.gz
Author: blipk
Author-email: blipk+@github.com
License: MIT license
Project-URL: Changelog, https://github.com/blipk/streamlitextras/commits/
Project-URL: Documentation, https://streamlitextras.readthedocs.io/en/stable/index.html
Keywords: streamlitextras,streamlit,router,authenticator,javascript,cookie,thread
Classifier: Development Status :: 5 - Production/Stable
Classifier: License :: OSI Approved :: MIT License
Classifier: Operating System :: OS Independent
Classifier: Intended Audience :: Developers
Classifier: Natural Language :: English
Classifier: Topic :: Internet :: WWW/HTTP
Classifier: Topic :: Internet :: WWW/HTTP :: Browsers
Classifier: Topic :: Software Development :: Libraries
Classifier: Programming Language :: Python
Classifier: Programming Language :: Python :: 3
Classifier: Programming Language :: Python :: 3.10
Classifier: Programming Language :: Python :: 3 :: Only
Classifier: Programming Language :: Python :: Implementation :: PyPy
Classifier: Programming Language :: Python :: Implementation :: CPython
Requires-Python: >=3.10
License-File: LICENCE
Requires-Dist: streamlit >=1.23.1
Requires-Dist: streamlit-javascript
Requires-Dist: loguru
Requires-Dist: requests
Requires-Dist: gcloud
Requires-Dist: pyjwt
Requires-Dist: firebase
Requires-Dist: pyrebase4
Requires-Dist: sseclient
Requires-Dist: PyCryptodome
Requires-Dist: requests-toolbelt
Requires-Dist: firebase-admin
Requires-Dist: google-cloud-storage
Provides-Extra: dev
Requires-Dist: Sphinx ==5.2.3 ; (python_version >= "3.10") and extra == 'dev'
Requires-Dist: sphinx-autobuild ==2021.3.14 ; (python_version >= "3.10") and extra == 'dev'
Requires-Dist: sphinx-rtd-theme ==1.0.0 ; (python_version >= "3.10") and extra == 'dev'
Requires-Dist: docutils ==0.16 ; (python_version >= "3.10") and extra == 'dev'
Requires-Dist: sphinxcontrib-apidoc ; (python_version >= "3.10") and extra == 'dev'
